{
  "project_info": {
    "project_number": "155714069238",
    "firebase_url": "https://teambuilder-8e58d.firebaseio.com",
    "project_id": "teambuilder-8e58d",
    "storage_bucket": "teambuilder-8e58d.appspot.com"
  },
  "client": [
    {
      "client_info": {
        "mobilesdk_app_id": "1:155714069238:android:4db29fec9c71589c7582d7",
        "android_client_info": {
          "package_name": "net.andrasia.teambuilder"
        }
      },
      "oauth_client": [
        {
          "client_id": "155714069238-elfetd280lu5usrl84a7fb0viqjpqrgc.apps.googleusercontent.com",
          "client_type": 1,
          "android_info": {
            "package_name": "net.andrasia.teambuilder",
            "certificate_hash": "6ad53d12109f7db1d8e2fd576232d62a97970c0d"
          }
        },
        {
          "client_id": "155714069238-j3s1b7ee9dajstnq4c1g1h1c6mfnn2m7.apps.googleusercontent.com",
          "client_type": 1,
          "android_info": {
            "package_name": "net.andrasia.teambuilder",
            "certificate_hash": "051a7dcb845f1311d79f81dcb58c5bd576812011"
          }
        },
        {
          "client_id": "155714069238-ioabr89m1g5f50rhnt7lte7lm15rm4n2.apps.googleusercontent.com",
          "client_type": 1,
          "android_info": {
            "package_name": "net.andrasia.teambuilder",
            "certificate_hash": "309f68f2ad702d2f20089d5b80f9b8c9d2f468db"
          }
        }
      ],
      "api_key": [
        {
          "current_key": "AIzaSyCTEC8NsyJUuHdExe7ZdURkvcik9PMbIAM"
        }
      ],
      "services": {
        "appinvite_service": {
          "other_platform_oauth_client": []
        }
      }
    }
  ],
  "configuration_version": "1"
}